nyct_gtfs/__init__.py
nyct_gtfs/cpp_parser_wrapper.py
nyct_gtfs/feed.py
nyct_gtfs/gtfs_static_types.py
nyct_gtfs/stop_time_update.py
nyct_gtfs/trip.py
nyct_gtfs/compiled_gtfs/__init__.py
nyct_gtfs/compiled_gtfs/gtfs_realtime_pb2.py
nyct_gtfs/compiled_gtfs/nyct_subway_pb2.py
nyct_gtfs/gtfs_static/stops.txt
nyct_gtfs/gtfs_static/trips.txt
nyct_gtfs-2.0.0.dist-info/LICENSE.txt
nyct_gtfs-2.0.0.dist-info/METADATA
nyct_gtfs-2.0.0.dist-info/WHEEL
nyct_gtfs-2.0.0.dist-info/top_level.txt
nyct_gtfs-2.0.0.dist-info/RECORD
