Metadata-Version: 2.1
Name: nyct-gtfs
Version: 2.0.0
Summary: Real-time NYC subway data parsing for humans
Home-page: https://github.com/Andrew-Dickinson/nyct-gtfs
Author: Andrew Dickinson
Author-email: andrew.dickinson.0216@gmail.com
License: MIT
Classifier: License :: OSI Approved :: MIT License
Classifier: Programming Language :: Python :: 3
Classifier: Operating System :: OS Independent
License-File: LICENSE.txt
Requires-Dist: requests
Requires-Dist: protobuf==4.25.3
Requires-Dist: httpx
